Metadata-Version: 1.0
Name: distributions-eddiefroufrou
Version: 0.1
Summary: distributions_eddiefroufrou
Home-page: UNKNOWN
Author: eddie froufrou
Author-email: edwinjmeyers@gmail.com
License: UNKNOWN
Platform: UNKNOWN
